gmpg/__init__.py
gmpg/__main__.py
gmpg/_pkg/__init__.py
gmpg/_pkg/install.py
gmpg/_pkg/licensing/__init__.py
gmpg/_pkg/licensing/licenses.json
gmpg/_pkg/listing.py
gmpg/_pkg/runinenv
gmpg/_pkg/system.py
gmpg/analysis.py
gmpg/git.py
gmpg/ide.py
gmpg/pkg.py
gmpg-0.1.40.dist-info/METADATA
gmpg-0.1.40.dist-info/entry_points.txt
gmpg-0.1.40.dist-info/WHEEL
gmpg-0.1.40.dist-info/RECORD
