Metadata-Version: 2.1
Name: gmpg
Version: 0.1.40
Summary: tools for metamodern software development
Home-page: https://ragt.ag/code/projects/gmpg
License: BSD-2-Clause
Keywords: black,git,isort,poetry,pydeps,pyright,pytest,radon
Author: Angelo Gladding
Author-email: angelo@ragt.ag
Requires-Python: >=3.9,<3.11
Classifier: License :: OSI Approved :: BSD License
Classifier: Programming Language :: Python :: 3
Classifier: Programming Language :: Python :: 3.9
Classifier: Programming Language :: Python :: 3.10
Requires-Dist: black (>=23.7.0,<24.0.0)
Requires-Dist: ipython (>=8.14.0,<9.0.0)
Requires-Dist: isort (>=5.11.4,<6.0.0)
Requires-Dist: mock (>=5.0.1,<6.0.0)
Requires-Dist: pendulum (>=2.1.2,<3.0.0)
Requires-Dist: pip (>=23.2.1,<24.0.0)
Requires-Dist: pydeps (>=1.11.0,<2.0.0)
Requires-Dist: pyright (>=1.1.322,<2.0.0)
Requires-Dist: pytest (>=7.4.0,<8.0.0)
Requires-Dist: pytest-cov (>=4.0.0,<5.0.0)
Requires-Dist: pytest-gevent (>=1.1.0,<2.0.0)
Requires-Dist: pytest-pep8 (>=1.0.6,<2.0.0)
Requires-Dist: radon (>=5.1.0,<6.0.0)
Requires-Dist: responses (>=0.22.0,<0.23.0)
Requires-Dist: toml (>=0.10.2,<0.11.0)
Requires-Dist: txtint (>=0.1)
Project-URL: Documentation, https://ragt.ag/code/projects/gmpg/api
Project-URL: Repository, https://ragt.ag/code/projects/gmpg.git
